sparkdatachallenge.py
sparkdatachallenge-0.1.1.dist-info/entry_points.txt
sparkdatachallenge-0.1.1.dist-info/LICENSE
sparkdatachallenge-0.1.1.dist-info/WHEEL
sparkdatachallenge-0.1.1.dist-info/METADATA
sparkdatachallenge-0.1.1.dist-info/RECORD
