Metadata-Version: 2.1
Name: sparkdatachallenge
Version: 0.1.1
Summary: <Enter a one-sentence description of this project here.>
Home-page: https://github.com/tomerten/sparkdatachallenge
License: MIT
Keywords: packaging,poetry
Author: Tom Mertens
Author-email: your.email@whatev.er
Requires-Python: >=3.8,<4.0
Classifier: License :: OSI Approved :: MIT License
Classifier: Programming Language :: Python :: 3
Classifier: Programming Language :: Python :: 3.8
Classifier: Programming Language :: Python :: 3.9
Requires-Dist: ipykernel (>=5.5.5,<6.0.0)
Requires-Dist: isort (>=5.8.0,<6.0.0)
Requires-Dist: matplotlib (>=3.4.2,<4.0.0)
Requires-Dist: nbsphinx (>=0.8.5,<0.9.0)
Requires-Dist: numpy (>=1.20.3,<2.0.0)
Requires-Dist: pandas (>=1.2.4,<2.0.0)
Requires-Dist: pylint (>=2.8.2,<3.0.0)
Requires-Dist: sympy (>=1.8,<2.0)
Project-URL: Repository, https://github.com/tomerten/sparkdatachallenge
